cartocss_doc_parser/__init__.py
cartocss_doc_parser-2.0.0.dist-info/LICENSE
cartocss_doc_parser-2.0.0.dist-info/METADATA
cartocss_doc_parser-2.0.0.dist-info/WHEEL
cartocss_doc_parser-2.0.0.dist-info/top_level.txt
cartocss_doc_parser-2.0.0.dist-info/RECORD
