Metadata-Version: 2.1
Name: cartocss-doc-parser
Version: 2.0.0
Summary: CartoCSS documentation parser.
Home-page: https://github.com/mondeja/cartocss-doc-parser
Author: Álvaro Mondéjar Rubio
Author-email: mondejar1994@gmail.com
License: BSD-3-Clause
Platform: UNKNOWN
Classifier: License :: OSI Approved :: BSD License
Classifier: Programming Language :: Python
Classifier: Programming Language :: Python :: 3
Classifier: Programming Language :: Python :: 3.7
Classifier: Programming Language :: Python :: 3.8
Classifier: Programming Language :: Python :: 3.9
Classifier: Programming Language :: Python :: 3.10
Classifier: Programming Language :: Python :: 3.11
Classifier: Topic :: Documentation
Classifier: Topic :: Internet
Classifier: Topic :: Internet :: WWW/HTTP :: Dynamic Content
Classifier: Topic :: Scientific/Engineering :: GIS
Requires-Python: >=3.7
Requires-Dist: beautifulsoup4
Requires-Dist: lxml
Provides-Extra: dev
Requires-Dist: black (==20.8b1) ; extra == 'dev'
Requires-Dist: bump2version (==1.0.1) ; extra == 'dev'
Requires-Dist: flake8 (==4.0.1) ; extra == 'dev'
Requires-Dist: flake8-implicit-str-concat (==0.2.0) ; extra == 'dev'
Requires-Dist: flake8-print (==4.0.0) ; extra == 'dev'
Requires-Dist: isort (==5.10.0) ; extra == 'dev'
Requires-Dist: pytest (==6.2.5) ; extra == 'dev'
Requires-Dist: pytest-cov (==3.0.0) ; extra == 'dev'
Requires-Dist: yamllint (==1.26.3) ; extra == 'dev'
Provides-Extra: lint
Requires-Dist: black (==20.8b1) ; extra == 'lint'
Requires-Dist: flake8 (==4.0.1) ; extra == 'lint'
Requires-Dist: flake8-implicit-str-concat (==0.2.0) ; extra == 'lint'
Requires-Dist: flake8-print (==4.0.0) ; extra == 'lint'
Requires-Dist: isort (==5.10.0) ; extra == 'lint'
Requires-Dist: yamllint (==1.26.3) ; extra == 'lint'
Provides-Extra: test
Requires-Dist: pytest (==6.2.5) ; extra == 'test'
Requires-Dist: pytest-cov (==3.0.0) ; extra == 'test'
